{
  "Yes": "是",
  "No": "否",
  "Enable": "启用",
  "Disable": "禁用",
  "Enabled": "已启用",
  "Disabled": "已禁用",
  "Remove": "移除",
  "Keep": "保留",
  "Options": "选项",
  "Wurst Options": "Wurst 选项",
  "Export Data": "导出数据",
  "View Changelog": "查看更新日志",
  "Open Keybind Manager": "打开按键绑定管理器",
  "Disable Telemetry": "禁用遥测",
  "Re-enable Telemetry": "重新启用遥测",
  "Reportable": "可举报",
  "Game Menu": "游戏菜单",
  "Statistics": "统计信息",
  "Auto": "自动",
  "Count": "计数",
  "Hidden": "隐藏",
  "Left": "左侧",
  "Right": "右侧",
  "Name": "名称",
  "Width": "宽度",
  "Always": "始终",
  "Only when outdated": "仅在版本过旧时",
  "Server Finder": "服务器查找器",
  "Search": "搜索",
  "Tutorial": "教程",
  "Back": "返回",
  "Cancel": "取消",
  "Clean Up": "清理",
  "This will search for servers with similar IPs": "这将搜索与输入 IP 相近的服务器",
  "to the IP you type into the field below.": "目标是你在下方输入框中填写的 IP。",
  "The servers it finds will be added to your server list.": "找到的服务器会被添加到你的服务器列表中。",
  "Server address:": "服务器地址：",
  "Max. threads:": "最大线程数：",
  "Checked: %s / 1792": "已检测：%s / 1792",
  "Working: %s": "可用：%s",
  "Unknown Hosts: %s": "未知主机：%s",
  "Outdated Servers: %s": "过期服务器：%s",
  "Failed Ping: %s": "Ping 失败：%s",
  "\"Grief me\" Servers: %s": "\"Grief me\" 服务器：%s",
  "\u00a7cRemove all Servers: %s": "\u00a7c移除全部服务器：%s",
  "Rename all Servers: %s": "重命名全部服务器：%s",
  "Please select the servers you want to remove:": "请选择你要移除的服务器：",
  "Start the Clean Up with the settings": "使用上面的设置开始清理",
  "you specified above.": "你已在上方指定这些设置。",
  "It might look like the game is not": "游戏可能会看起来像是",
  "responding for a couple of seconds.": "在几秒内没有响应。",
  "Servers that clearly don't exist.": "明显不存在的服务器。",
  "Servers that run a different Minecraft": "运行了不同 Minecraft",
  "version than you.": "版本的服务器。",
  "All servers that failed the last ping.": "上次 Ping 失败的所有服务器。",
  "Make sure that the last ping is complete": "请确保上次 Ping 已完全结束",
  "before you do this. That means: Go back,": "再执行此操作。也就是：先返回，",
  "press the refresh button and wait until": "按刷新按钮并等待直到",
  "all servers are done refreshing.": "所有服务器都刷新完成。",
  "All servers where the name starts with \"Grief me\"": "名称以 \"Grief me\" 开头的所有服务器",
  "Useful for removing servers found by ServerFinder.": "适合清理由 ServerFinder 找到的服务器。",
  "This will completely clear your server": "这会完全清空你的服务器",
  "list. \u00a7cUse with caution!\u00a7r": "列表。\u00a7c请谨慎使用！\u00a7r",
  "Renames your servers to \"Grief me #1\",": "将你的服务器重命名为 \"Grief me #1\"，",
  "\"Grief me #2\", etc.": "\"Grief me #2\" 等。",
  "Grief me": "待破坏",
  "Grief me #%s": "待破坏 #%s",
  "\u00a72Searching...": "\u00a72搜索中...",
  "\u00a72Resolving...": "\u00a72解析中...",
  "\u00a74Unknown Host!": "\u00a74未知主机！",
  "\u00a74Cancelled!": "\u00a74已取消！",
  "\u00a72Done!": "\u00a72完成！",
  "\u00a74An error occurred!": "\u00a74发生错误！",
  "Wurst Server Pinger #%s": "Wurst 服务器 Ping 线程 #%s",
  "Pinging %s:%s...": "正在 Ping %s:%s...",
  "Ping successful: %s:%s": "Ping 成功：%s:%s",
  "Unknown host: %s:%s": "未知主机：%s:%s",
  "Ping failed: %s:%s": "Ping 失败：%s:%s",
  "Original message: ": "原始消息：",
  "The server is refusing to let you chat without enabling chat reports. Click \u00a7nhere\u00a7r to learn more.": "该服务器拒绝你在未启用聊天举报的情况下发言。点击\u00a7n这里\u00a7r了解更多。",
  "Syntax: %s": "用法：%s",
  "%s is blocked by TooManyHax.": "%s 已被 TooManyHax 屏蔽。",
  "Unknown command: .%s": "未知命令：.%s",
  "Use \".say %s\" to send it as a chat command.": "使用 \".say %s\" 将其作为聊天命令发送。",
  "Type \".help\" for a list of commands or \".say .%s\" to send it as a chat message.": "输入 \".help\" 查看命令列表，或使用 \".say .%s\" 将其作为聊天消息发送。",
  "Unknown hack: %s": "未知 Hack：%s",
  "Cannot cancel, Blink is already turned off!": "无法取消，Blink 已经关闭！",
  "Invalid page: %s": "无效页码：%s",
  "Not a number: %s": "不是数字：%s",
  "Invalid coordinates.": "无效坐标。",
  "Unknown key: %s": "未知按键：%s",
  "Invalid color: %s": "无效颜色：%s",
  "Invalid effect: %s": "无效效果：%s",
  "Value must be a number.": "数值必须是数字。",
  "The maximum distance is 10 blocks.": "最大距离为 10 格。",
  "Could not find a path.": "找不到路径。",
  "Cannot refresh: no previous path.": "无法刷新：没有上一次路径。",
  "No previous position on .path.": ".path 没有上一次位置。",
  "No longer annoying %s.": "已停止烦扰 %s。",
  "Now annoying %s.": "现在开始烦扰 %s。",
  "Annoying yourself is a bad idea!": "烦扰你自己可不是个好主意！",
  "Added 1 alt.": "已添加 1 个小号。",
  "Added %s alt.": "已添加 %s 个小号。",
  "Added %s alts.": "已添加 %s 个小号。",
  "Added friend \"%s\".": "已添加好友 \"%s\"。",
  "Removed friend \"%s\".": "已移除好友 \"%s\"。",
  "\"%s\" is already in your friends list.": "\"%s\" 已在你的好友列表中。",
  "\"%s\" is not in your friends list.": "\"%s\" 不在你的好友列表中。",
  "All friends removed. Oof.": "已移除所有好友。唉。",
  "Current friends: %s": "当前好友数：%s",
  "Friends list (page %s/%s)": "好友列表（第 %s/%s 页）",
  "Total: %s command": "总计：%s 条命令",
  "Total: %s commands": "总计：%s 条命令",
  "Total: %s profile": "总计：%s 个配置",
  "Total: %s profiles": "总计：%s 个配置",
  "Total: %s keybind": "总计：%s 个按键绑定",
  "Total: %s keybinds": "总计：%s 个按键绑定",
  "Total: %s block": "总计：%s 个方块",
  "Total: %s blocks": "总计：%s 个方块",
  "Total: %s item": "总计：%s 个物品",
  "Total: %s items": "总计：%s 个物品",
  "Total: %s blocked feature": "总计：%s 个被屏蔽功能",
  "Total: %s blocked features": "总计：%s 个被屏蔽功能",
  "Command list (page %s/%s)": "命令列表（第 %s/%s 页）",
  "Available help for .%s:": ".%s 的可用帮助：",
  "Server version: %s": "服务器版本：%s",
  "Showing inventory of %s.": "正在查看 %s 的背包。",
  "Keybind set: %s -> %s": "已设置按键绑定：%s -> %s",
  "Keybind removed: %s -> %s": "已移除按键绑定：%s -> %s",
  "Keybind list (page %s/%s)": "按键绑定列表（第 %s/%s 页）",
  "Keybind profile list (page %s/%s)": "按键绑定配置列表（第 %s/%s 页）",
  "Keybinds loaded: %s": "按键绑定已加载：%s",
  "Keybinds saved: %s": "按键绑定已保存：%s",
  "Settings loaded: %s": "设置已加载：%s",
  "Settings saved: %s": "设置已保存：%s",
  "Settings profile list (page %s/%s)": "设置配置列表（第 %s/%s 页）",
  "Hacks loaded: %s": "Hack 已加载：%s",
  "Hacks saved: %s": "Hack 已保存：%s",
  "Enabled hacks profile list (page %s/%s)": "启用 Hack 配置列表（第 %s/%s 页）",
  "TooManyHax list (page %s/%s)": "TooManyHax 列表（第 %s/%s 页）",
  "TooManyHax profile loaded: %s": "TooManyHax 配置已加载：%s",
  "TooManyHax profile saved: %s": "TooManyHax 配置已保存：%s",
  "TooManyHax profile list (page %s/%s)": "TooManyHax 配置列表（第 %s/%s 页）",
  "All keybinds removed.": "已移除全部按键绑定。",
  "All keybinds reset to defaults.": "按键绑定已重置为默认值。",
  "Nothing to remove.": "没有可移除的内容。",
  "Profile '%s' doesn't exist.": "配置 '%s' 不存在。",
  "Profile '%s' is corrupted: %s": "配置 '%s' 已损坏：%s",
  "Couldn't load profile: %s": "无法加载配置：%s",
  "Couldn't save profile: %s": "无法保存配置：%s",
  "The %s is not safe to block.": "%s 不适合被屏蔽。",
  "The %s is already blocked.": "%s 已经被屏蔽。",
  "The %s is not blocked.": "%s 未被屏蔽。",
  "Added %s to TooManyHax list.": "已将 %s 添加到 TooManyHax 列表。",
  "Removed %s from TooManyHax list.": "已将 %s 从 TooManyHax 列表移除。",
  "Enable TooManyHax to see the effect.": "启用 TooManyHax 后才能看到效果。",
  "All* features blocked.": "所有*功能已屏蔽。",
  "are required for Wurst to work properly.": "是 Wurst 正常运行所必需的。",
  "All features unblocked.": "已取消屏蔽所有功能。",
  "A feature named '%s' could not be found": "找不到名为 '%s' 的功能",
  "%s %s already contains %s": "%s %s 已包含 %s",
  "%s %s does not contain %s": "%s %s 不包含 %s",
  "%s %s is not a block setting.": "%s %s 不是方块设置。",
  "%s %s is not a checkbox setting.": "%s %s 不是复选框设置。",
  "%s %s is not a color setting.": "%s %s 不是颜色设置。",
  "%s %s is not a mode setting.": "%s %s 不是模式设置。",
  "%s %s is not a slider setting.": "%s %s 不是滑块设置。",
  "%s %s is not a BlockList setting.": "%s %s 不是 BlockList 设置。",
  "%s %s is not a ItemList setting.": "%s %s 不是 ItemList 设置。",
  "A mode named '%s' in %s %s does not exist.": "%s %s 中不存在名为 '%s' 的模式。",
  "Item%s created.": "物品%s已创建。",
  "Item copied.": "物品已复制。",
  "Item enchanted.": "物品已附魔。",
  "Item modified.": "物品已修改。",
  "Item repaired.": "物品已修复。",
  "Potion modified.": "药水已修改。",
  "Effect removed.": "效果已移除。",
  "Component data copied to clipboard.": "组件数据已复制到剪贴板。",
  "NBT data copied to clipboard.": "NBT 数据已复制到剪贴板。",
  "IP copied to clipboard.": "IP 已复制到剪贴板。",
  "Position copied to clipboard.": "坐标已复制到剪贴板。",
  "Components: %s": "组件：%s",
  "NBT: %s": "NBT：%s",
  "IP: %s": "IP：%s",
  "Position: %s": "坐标：%s",
  "Renamed item to \"\u00a7o%s\u00a7r\".": "已将物品重命名为 \"\u00a7o%s\u00a7r\"。",
  "Creative mode only.": "仅创造模式可用。",
  "Survival mode only.": "仅生存模式可用。",
  "You must hold a potion in your main hand.": "你必须在主手持有药水。",
  "You must hold a written book in your main hand.": "你必须在主手持有成书。",
  "You must hold an item in your main hand.": "你必须在主手持有物品。",
  "You need an item in your hand.": "你手上需要有一个物品。",
  "There is no item in your hand.": "你手上没有物品。",
  "This item can't take damage.": "这个物品无法承受耐久损耗。",
  "This item is not damaged.": "这个物品没有损耗。",
  "There is nothing to clip through!": "没有可穿过的方块！",
  "There are no free blocks where you can fit!": "没有可容纳你的空方块！",
  "Can't jump in mid-air.": "不能在空中跳跃。",
  "Can't check server version in singleplayer.": "单人模式下无法检查服务器版本。",
  "Player not found.": "未找到玩家。",
  "Failed to export data: %s": "导出数据失败：%s",
  "Opens the changelog in your browser.": "在浏览器中打开更新日志。",
  "Cleans up your server list.": "清理你的服务器列表。",
  "To use it, press the 'Clean Up' button on the server selection screen.": "使用方法：在服务器选择界面点击“Clean Up”按钮。",
  "To disable Wurst, go to the Statistics screen and press the \"Disable Wurst\" button.": "要禁用 Wurst，请前往统计信息界面并点击“Disable Wurst”按钮。",
  "It will turn into an \"Enable Wurst\" button once pressed.": "点击后它会变成“Enable Wurst”按钮。",
  "Removes the \"Enable Wurst\" button as soon as you close the Statistics screen.": "在你关闭统计信息界面后立即移除“Enable Wurst”按钮。",
  "You will have to restart the game to re-enable Wurst.": "你需要重启游戏才能重新启用 Wurst。",
  "This is just a shortcut to let you open the Keybind Manager from within the GUI. Normally you would go to Wurst Options > Keybinds.": "这只是一个快捷方式，让你在 GUI 内直接打开按键绑定管理器。通常你需要进入 Wurst Options > Keybinds。",
  "Wurst adds a \"Last Server\" button to the server selection screen that automatically brings you back to the last server you played on.": "Wurst 会在服务器选择界面添加一个“Last Server”按钮，自动带你回到上次游玩的服务器。",
  "Useful when you get kicked and/or have a lot of servers.": "当你被踢出，或服务器太多时非常有用。",
  "Disables the \"required\" telemetry that Mojang introduced in 22w46a. Turns out it's not so required after all.": "禁用 Mojang 在 22w46a 引入的“必需”遥测。事实证明它并没有那么必需。",
  "Whenever you get kicked from a server, Wurst gives you a \"Reconnect\" button that lets you instantly join again.": "每当你从服务器被踢出时，Wurst 会提供一个“Reconnect”按钮，让你立即重连。",
  "Allows you to find easy-to-grief Minecraft servers quickly and easily. To use it, press the 'Server Finder' button on the server selection screen.": "让你快速轻松地找到容易破坏的 Minecraft 服务器。使用方法：在服务器选择界面点击“Server Finder”按钮。",
  "Allows you to quickly toggle hacks while playing.": "允许你在游戏时快速切换 Hack。",
  "Use the arrow keys to navigate.": "使用方向键进行导航。",
  "Change the \u00a76HackList \u00a76Position\u00a7r setting to \u00a76Right\u00a7r to prevent TabGUI from overlapping with the HackList.": "将 \u00a76HackList \u00a76Position\u00a7r 设置改为 \u00a76Right\u00a7r，可避免 TabGUI 与 HackList 重叠。",
  "Bypasses anti-Fabric plugins by pretending to be a vanilla client.": "通过伪装成原版客户端来绕过反 Fabric 插件。",
  "Wurst has its own capes! Only Wurst users can see them.": "Wurst 有自己的披风！只有 Wurst 用户能看到。",
  "Shows a list of active hacks on the screen.": "在屏幕上显示已启用 Hack 列表。",
  "Shows the Wurst logo and version on the screen.": "在屏幕上显示 Wurst 图标与版本。",
  "Background color.": "背景颜色。",
  "Text color.": "文本颜色。",
  "Color of the HackList text.": "HackList 文本颜色。",
  "Only visible when \u00a76RainbowUI\u00a7r is disabled.": "仅在 \u00a76RainbowUI\u00a7r 被禁用时显示。",
  "Which side of the screen the HackList should be shown on.": "HackList 显示在屏幕的哪一侧。",
  "Change this to \u00a7lRight\u00a7r when using TabGUI.": "使用 TabGUI 时请将其改为 \u00a7lRight\u00a7r。",
  "Determines how the HackList entries are sorted.": "决定 HackList 条目的排序方式。",
  "Only visible when \u00a76Mode\u00a7r is set to \u00a76Auto\u00a7r.": "仅当 \u00a76Mode\u00a7r 设置为 \u00a76Auto\u00a7r 时显示。",
  "When enabled, entries slide into and out of the HackList as hacks are enabled and disabled.": "启用后，Hack 开关时条目会滑入滑出 HackList。"
  ,
  "Toggles a hack.": "切换一个 Hack 的开关状态。",
  "Enables, disables or cancels Blink.": "启用、禁用或取消 Blink。",
  "Instantly disconnects from the server.": "立即与服务器断开连接。",
  "Adds a player to your alt list.": "将玩家添加到你的小号列表。",
  "Changes the author of a written book.": "修改成书作者。",
  "and/or wearing. Requires creative mode.": "或其已穿戴的物品。需要创造模式。",
  "Gives you an item with custom NBT data.": "给予你带自定义 NBT 数据的物品。",
  "Shows your current position.": "显示你当前坐标。",
  "Shows help for a command or a list of commands.": "显示某个命令的帮助，或显示命令列表。",
  "Protects the given entity from other entities.": "保护指定实体免受其他实体攻击。",
  "Makes you jump.": "让你跳跃。",
  "Shortcut for '.binds add'.": "'.binds add' 的快捷命令。",
  "Shortcut for '.binds remove'.": "'.binds remove' 的快捷命令。",
  "Shortcut for '.blocklist X-Ray Ores'.": "'.blocklist X-Ray Ores' 的快捷命令。",
  "Shortcut for /gamemode.": "/gamemode 的快捷命令。",
  "Automatically destroys all blocks in the selected area.": "自动摧毁所选区域内所有方块。",
  "Shows the number of features and some other": "显示功能数量以及其他",
  "statistics.": "统计信息。",
  "Follows the given entity.": "跟随指定实体。",
  "Shows the IP of the server you are currently": "显示你当前所在服务器的 IP，",
  "connected to or copies it to the clipboard.": "或将其复制到剪贴板。",
  "Allows you to modify component data of items.": "允许你修改物品的组件数据。",
  "Renames the item in your hand.": "重命名你手中的物品。",
  "Changes a block setting of a feature. Allows you": "修改某个功能的方块设置。并允许你",
  "to change these settings through keybinds.": "通过按键绑定修改这些设置。",
  "Changes a slider setting of a feature. Allows you to": "修改某个功能的滑块设置。并允许你",
  "move sliders through keybinds.": "通过按键绑定调节滑块。",
  "Applies the given amount of damage.": "造成指定数值的伤害。",
  "Spawns a dancing taco on your hotbar.": "在你的快捷栏生成一只跳舞玉米卷。",
  "Use $ for colors, use $$ for $.": "使用 $ 表示颜色，使用 $$ 表示字面量 $。",
  "Lets you clip through blocks vertically.": "让你垂直穿过方块。",
  "Useful for labyrinths and caves.": "适用于迷宫和洞穴。",
  "Repairs the held item. Requires creative mode.": "修复手持物品。需要创造模式。",
  "Manages your friends list.": "管理你的好友列表。",
  "Walks or flies you to a specific location.": "让你步行或飞行到指定位置。",
  "Shows the shortest path to a specific point.": "显示到指定点的最短路径。",
  "Shows the version of the server": "显示服务器版本",
  "you are currently connected to.": "（你当前连接的服务器）。",
  "Teleports you up to 22 blocks away.": "将你传送到最远 22 格之外。",
  "Shows you the NBT data of an item.": "显示物品的 NBT 数据。",
  "Changes a checkbox setting of a feature. Allows you": "修改某个功能的复选框设置。并允许你",
  "to toggle checkboxes through keybinds.": "通过按键绑定切换复选框。",
  "Changes a color setting of a feature. Allows you": "修改某个功能的颜色设置。并允许你",
  "to set RGB values through keybinds.": "通过按键绑定设置 RGB 值。",
  "Allows you to make profiles of your settings.": "允许你创建设置配置。",
  "Makes RemoteView target a specific entity.": "让 RemoteView 锁定指定实体。",
  "Allows to manage which hacks should be blocked": "允许管理哪些 Hack 应被屏蔽",
  "when TooManyHax is enabled.": "（在 TooManyHax 启用时）。",
  "Shows you the component data of an item.": "显示物品的组件数据。",
  "Sends the given chat message, even if it starts with a": "发送给定聊天消息，即使它以",
  "dot.": "点号开头。",
  "Changes the effects of the held potion.": "修改手持药水的效果。",
  "Middle click friends": "中键好友",
  "Add/remove friends by clicking them with the middle mouse button.": "使用鼠标中键点击玩家来添加/移除好友。",
  "Get Position": "获取坐标",
  "Copy to clipboard: .getpos copy": "复制到剪贴板：.getpos copy",
  "Get IP": "获取 IP",
  "Copy to clipboard: .ip copy": "复制到剪贴板：.ip copy",
  "Get Server Version": "获取服务器版本",
  "Show Statistics": "显示统计信息",
  "This is just a pre-release! It doesn't (yet) have all of the features of Wurst 7.0! See download page for details.": "这只是预发布版本！它（暂时）还没有 Wurst 7.0 的全部功能！详情请见下载页面。",
  "Can't find book data.": "找不到书本数据。",
  "Minimum amount is 1.": "最小数量为 1。",
  "Maximum amount is 7.": "最大数量为 7。",
  "Note: The amount is in half-hearts.": "注意：该数值以半颗心为单位。",
  "To apply more damage, run the command multiple times.": "若要造成更多伤害，请多次执行该命令。",
  "Amount cannot be less than 1.": "数量不能小于 1。",
  "Amount cannot be more than 64.": "数量不能大于 64。",
  "NBT data is invalid.": "NBT 数据无效。",
  "Cannot damage in creative mode.": "创造模式下无法造成此伤害。",
  "Tacos don't need arguments!": "Taco 命令不需要参数！",
  "Feature name must not contain spaces: %s": "功能名称不能包含空格：%s",
  "Running Wurst command": "正在运行 Wurst 命令",
  "Affected command": "受影响命令",
  "Command input": "命令输入",
  "Unknown command: .": "未知命令：.",
  "\"%s\" could not be found.": "找不到 \"%s\"。",
  "Entity \"%s\" could not be found.": "找不到实体 \"%s\"。",
  "Player \"%s\" could not be found.": "找不到玩家 \"%s\"。"
  ,
  "Leave": "离开",
  "Jump": "跳跃",
  "Be a BOSS!": "当个大佬！",
  "hack": "Hack",
  "command": "命令",
  "feature": "功能",
  "Invalid %s: %s": "无效的%s：%s",
  "%s can't be zero": "%s 不能为 0",
  "%s %s (page %s/%s)": "%s %s（第 %s/%s 页）",
  "- %s": "- %s"
}
